CHANGES.txt
MANIFEST.in
README.txt
buildout.cfg
setup.cfg
setup.py
src/minitage/__init__.py
src/minitage.recipe.cmmi.egg-info/PKG-INFO
src/minitage.recipe.cmmi.egg-info/SOURCES.txt
src/minitage.recipe.cmmi.egg-info/dependency_links.txt
src/minitage.recipe.cmmi.egg-info/entry_points.txt
src/minitage.recipe.cmmi.egg-info/namespace_packages.txt
src/minitage.recipe.cmmi.egg-info/not-zip-safe
src/minitage.recipe.cmmi.egg-info/requires.txt
src/minitage.recipe.cmmi.egg-info/top_level.txt
src/minitage/recipe/__init__.py
src/minitage/recipe/cmmi/__init__.py
src/minitage/recipe/cmmi/cmmi.py
src/minitage/recipe/cmmi/tests/__init__.py
src/minitage/recipe/cmmi/tests/cmmi.txt
src/minitage/recipe/cmmi/tests/test_recipe.py
src/minitage/recipe/cmmi/tests/tests.py